ctmodbus/__init__.py
ctmodbus/commands.py
ctmodbus/common.py
ctmodbus-0.5.3.dist-info/entry_points.txt
ctmodbus-0.5.3.dist-info/LICENSE
ctmodbus-0.5.3.dist-info/WHEEL
ctmodbus-0.5.3.dist-info/METADATA
ctmodbus-0.5.3.dist-info/RECORD
