Metadata-Version: 2.1
Name: ctmodbus
Version: 0.5.3
Summary: A highly flexible Modbus tool made for penetration testers
Home-page: https://www.controlthings.io
License: LGPL-3.0-or-later
Keywords: Modbus,test,ICS,control,ControlThings
Author: Justin Searle
Author-email: justin@controlthings.io
Requires-Python: >=3.6,<4.0
Classifier: Development Status :: 5 - Production/Stable
Classifier: Intended Audience :: Developers
Classifier: Intended Audience :: Information Technology
Classifier: Intended Audience :: Manufacturing
Classifier: Intended Audience :: Other Audience
Classifier: Intended Audience :: Science/Research
Classifier: License :: OSI Approved :: GNU Lesser General Public License v3 or later (LGPLv3+)
Classifier: Operating System :: Microsoft :: Windows
Classifier: Operating System :: POSIX
Classifier: Operating System :: Unix
Classifier: Programming Language :: Python :: 3
Classifier: Programming Language :: Python :: 3.6
Classifier: Programming Language :: Python :: 3.7
Classifier: Programming Language :: Python :: 3.8
Classifier: Programming Language :: Python :: 3.9
Classifier: Topic :: Utilities
Requires-Dist: ctui (>=0.7.3,<0.8.0)
Requires-Dist: psutil (>=5.8.0,<6.0.0)
Requires-Dist: pymodbus (>=2.4.0,<3.0.0)
Requires-Dist: pyserial (>=3.5,<4.0)
Requires-Dist: tabulate (>=0.8.9,<0.9.0)
Project-URL: Repository, https://github.com/ControlThings-io/ctmodbus
